README.txt
setup.py
cull/__init__.py
cull/cull.py
cull.egg-info/PKG-INFO
cull.egg-info/SOURCES.txt
cull.egg-info/dependency_links.txt
cull.egg-info/entry_points.txt
cull.egg-info/requires.txt
cull.egg-info/top_level.txt