Metadata-Version: 1.0
Name: cull
Version: 0.8
Summary: A cli parser for AWS output.
Home-page: https://pypi.python.org/pypi/cull
Author: Travis Dolan
Author-email: travis.dolan@gmail.com
License: LICENSE.txt
Platform: UNKNOWN
